{
  "project_info": {
    "project_number": "317818174779",
    "project_id": "transmaa-9fa8e",
    "storage_bucket": "transmaa-9fa8e.appspot.com"
  },
  "client": [
    {
      "client_info": {
        "mobilesdk_app_id": "1:317818174779:android:65592047e9b60931660b1e",
        "android_client_info": {
          "package_name": "com.example.customer"
        }
      },
      "oauth_client": [],
      "api_key": [
        {
          "current_key": "AIzaSyCjK6C4Celx1bB8Ty6vemK-7d7TUlnfgyo"
        }
      ],
      "services": {
        "appinvite_service": {
          "other_platform_oauth_client": []
        }
      }
    },
    {
      "client_info": {
        "mobilesdk_app_id": "1:317818174779:android:415bf84657b51323660b1e",
        "android_client_info": {
          "package_name": "com.example.transmaacode"
        }
      },
      "oauth_client": [],
      "api_key": [
        {
          "current_key": "AIzaSyCjK6C4Celx1bB8Ty6vemK-7d7TUlnfgyo"
        }
      ],
      "services": {
        "appinvite_service": {
          "other_platform_oauth_client": []
        }
      }
    }
  ],
  "configuration_version": "1"
}